dimweb_persona_bot/__init__.py
dimweb_persona_bot/utils.py
dimweb_persona_bot/database_logger/README.md
dimweb_persona_bot/database_logger/database-sandbox.ipynb
dimweb_persona_bot/database_logger/logger.py
dimweb_persona_bot/database_logger/migrations.json
dimweb_persona_bot/database_logger/models.py
dimweb_persona_bot/database_logger/migrations/0001_migration_202211200243.py
dimweb_persona_bot/database_logger/scripts/analize_database.py
dimweb_persona_bot/database_logger/scripts/check_last_predictions.sql
dimweb_persona_bot/database_logger/scripts/sandbox.md
dimweb_persona_bot/dataloaders/datasets.py
dimweb_persona_bot/dataloaders/focus_dataloaders.py
dimweb_persona_bot/dataloaders/lighting.py
dimweb_persona_bot/dataloaders/persona_chat_dataloaders.py
dimweb_persona_bot/dataloaders/causal_samplers/causal_samplers_hypothesis_1.py
dimweb_persona_bot/dataloaders/causal_samplers/causal_samplers_hypothesis_2.py
dimweb_persona_bot/dataloaders/causal_samplers/causal_samplers_hypothesis_3.py
dimweb_persona_bot/dataloaders/seq2seq_samplers/seq2seq_samplers_hypothesis_1.py
dimweb_persona_bot/dataloaders/seq2seq_samplers/seq2seq_samplers_hypothesis_2.py
dimweb_persona_bot/dataloaders/seq2seq_samplers/seq2seq_samplers_hypothesis_3.py
dimweb_persona_bot/dataloaders/seq2seq_samplers/seq2seq_samplers_hypothesis_4.py
dimweb_persona_bot/datasets_transformers/persona_chat_dataset_transformer.py
dimweb_persona_bot/eda/eda_scripts.py
dimweb_persona_bot/eda/tokens_length_causal_models.csv
dimweb_persona_bot/eda/tokens_length_seq2seq_models.csv
dimweb_persona_bot/experiments/causal_modeling_experiments/causal_hypothesis_1.py
dimweb_persona_bot/experiments/causal_modeling_experiments/causal_hypothesis_2.py
dimweb_persona_bot/experiments/causal_modeling_experiments/causal_hypothesis_3.py
dimweb_persona_bot/experiments/seq2seq_modeling_experiments/seq2seq_hypothesis_1.py
dimweb_persona_bot/experiments/seq2seq_modeling_experiments/seq2seq_hypothesis_2.py
dimweb_persona_bot-0.0.6.dist-info/METADATA
dimweb_persona_bot-0.0.6.dist-info/WHEEL
dimweb_persona_bot-0.0.6.dist-info/licenses/LICENSE
dimweb_persona_bot-0.0.6.dist-info/RECORD
